pyeasythymio_kurniawano/__init__.py
pyeasythymio_kurniawano/easythymio.py
pyeasythymio_kurniawano-0.0.2.dist-info/METADATA
pyeasythymio_kurniawano-0.0.2.dist-info/WHEEL
pyeasythymio_kurniawano-0.0.2.dist-info/licenses/LICENSE
pyeasythymio_kurniawano-0.0.2.dist-info/RECORD
