Metadata-Version: 2.4
Name: pyeasythymio_kurniawano
Version: 0.0.2
Summary: A small package to allow Thymio to be coded using Python in sequential manner.
Project-URL: Homepage, https://github.com/pypa/sampleproject
Project-URL: Issues, https://github.com/pypa/sampleproject/issues
Author-email: Oka Kurniawan <oka_kurniawan@sutd.edu.sg>
License-Expression: MIT
License-File: LICENSE
Classifier: Operating System :: OS Independent
Classifier: Programming Language :: Python :: 3
Requires-Python: >=3.12
Requires-Dist: tdmclient
